fediverse_graphs/__init__.py
fediverse_graphs/main.py
fediverse_graphs-0.9.2.dist-info/licenses/LICENSE
tests/__init__.py
tests/test_loader.py
fediverse_graphs-0.9.2.dist-info/METADATA
fediverse_graphs-0.9.2.dist-info/WHEEL
fediverse_graphs-0.9.2.dist-info/top_level.txt
fediverse_graphs-0.9.2.dist-info/RECORD
